setup.cfg
setup.py
htop/__init__.py
htop/__version__.py
htop/htop.py
htop.egg-info/PKG-INFO
htop.egg-info/SOURCES.txt
htop.egg-info/dependency_links.txt
htop.egg-info/requires.txt
htop.egg-info/top_level.txt
htop/test/__init__.py
htop/test/htop-tests.py