Metadata-Version: 1.1
Name: htop
Version: 1.0
Summary: A lhk 1st training project
Home-page: https://gitlab.lohika.com/vbakhor/python-htop
Author: Volodymyr B.
Author-email: pypa-dev@googlegroups.com
License: The MIT License (MIT)
